proovl-sms/__init__.py
proovl-sms/proovl_sms.py
proovl_sms/__init__.py
proovl_sms/proovl_sms.py
proovl_sms-0.1.8.dist-info/LICENSE.txt
proovl_sms-0.1.8.dist-info/METADATA
proovl_sms-0.1.8.dist-info/WHEEL
proovl_sms-0.1.8.dist-info/top_level.txt
proovl_sms-0.1.8.dist-info/RECORD
